redisdol/__init__.py
redisdol-0.0.3.dist-info/LICENSE
redisdol-0.0.3.dist-info/METADATA
redisdol-0.0.3.dist-info/WHEEL
redisdol-0.0.3.dist-info/top_level.txt
redisdol-0.0.3.dist-info/RECORD
