Metadata-Version: 2.1
Name: redisdol
Version: 0.0.3
Summary: redis with a simple (dict-like or list-like) interface
Home-page: https://github.com/i2mint/redisdol
Author: OtoSense
License: apache-2.0
Platform: any
Requires-Dist: dol
Requires-Dist: redis
